iosanita.policy-1.0.5-py3.10-nspkg.pth
iosanita/policy/__init__.py
iosanita/policy/configure.zcml
iosanita/policy/interfaces.py
iosanita/policy/permissions.zcml
iosanita/policy/rejectanonymous.py
iosanita/policy/setuphandlers.py
iosanita/policy/testing.py
iosanita/policy/browser/__init__.py
iosanita/policy/browser/configure.zcml
iosanita/policy/browser/controlpanel.py
iosanita/policy/locales/README.rst
iosanita/policy/locales/__init__.py
iosanita/policy/locales/iosanita.policy.pot
iosanita/policy/locales/update.py
iosanita/policy/locales/update.sh
iosanita/policy/locales/en/LC_MESSAGES/iosanita.policy.mo
iosanita/policy/locales/en/LC_MESSAGES/iosanita.policy.po
iosanita/policy/profiles/default/browserlayer.xml
iosanita/policy/profiles/default/catalog.xml
iosanita/policy/profiles/default/controlpanel.xml
iosanita/policy/profiles/default/metadata.xml
iosanita/policy/profiles/default/rolemap.xml
iosanita/policy/profiles/default/registry/main.xml
iosanita/policy/profiles/default/registry/settings.xml
iosanita/policy/profiles/uninstall/browserlayer.xml
iosanita/policy/restapi/__init__.py
iosanita/policy/restapi/configure.zcml
iosanita/policy/restapi/controlpanel.py
iosanita/policy/restapi/services/__init__.py
iosanita/policy/restapi/services/configure.zcml
iosanita/policy/restapi/services/bandi_search_filters/__init__.py
iosanita/policy/restapi/services/bandi_search_filters/configure.zcml
iosanita/policy/restapi/services/bandi_search_filters/get.py
iosanita/policy/restapi/services/iosanita_settings/__init__.py
iosanita/policy/restapi/services/iosanita_settings/configure.zcml
iosanita/policy/restapi/services/iosanita_settings/get.py
iosanita/policy/restapi/services/search_filters/__init__.py
iosanita/policy/restapi/services/search_filters/configure.zcml
iosanita/policy/restapi/services/search_filters/get.py
iosanita/policy/restapi/services/search_tassonomie/__init__.py
iosanita/policy/restapi/services/search_tassonomie/configure.zcml
iosanita.policy-1.0.5.dist-info/LICENSE
iosanita.policy-1.0.5.dist-info/LICENSE.GPL
iosanita.policy-1.0.5.dist-info/LICENSE.rst
iosanita.policy-1.0.5.dist-info/METADATA
iosanita.policy-1.0.5.dist-info/WHEEL
iosanita.policy-1.0.5.dist-info/entry_points.txt
iosanita.policy-1.0.5.dist-info/namespace_packages.txt
iosanita.policy-1.0.5.dist-info/top_level.txt
iosanita.policy-1.0.5.dist-info/RECORD
