Metadata-Version: 2.1
Name: iosanita.policy
Version: 1.0.5
Summary: An add-on for Plone
Home-page: https://github.com/collective/iosanita.policy
Author: RedTurtle Technology
Author-email: sviluppo@redturtle.it
License: GPL version 2
Project-URL: PyPI, https://pypi.org/project/iosanita.policy/
Project-URL: Source, https://github.com/collective/iosanita.policy
Project-URL: Tracker, https://github.com/collective/iosanita.policy/issues
Keywords: Python Plone CMS
Classifier: Development Status :: 5 - Production/Stable
Classifier: Environment :: Web Environment
Classifier: Framework :: Plone
Classifier: Framework :: Plone :: Addon
Classifier: Framework :: Plone :: 6.0
Classifier: Programming Language :: Python
Classifier: Programming Language :: Python :: 3.8
Classifier: Programming Language :: Python :: 3.9
Classifier: Programming Language :: Python :: 3.10
Classifier: Programming Language :: Python :: 3.11
Classifier: Operating System :: OS Independent
Classifier: License :: OSI Approved :: GNU General Public License v2 (GPLv2)
Requires-Python: >=3.7
License-File: LICENSE
License-File: LICENSE.GPL
License-File: LICENSE.rst
Requires-Dist: setuptools
Requires-Dist: plone.api >=1.8.4
Requires-Dist: iosanita.contenttypes
Requires-Dist: collective.volto.enhancedlinks
Requires-Dist: collective.feedback
Requires-Dist: collective.volto.slimheader
Requires-Dist: iw.rejectanonymous
Requires-Dist: collective.volto.dropdownmenu
Requires-Dist: collective.volto.socialsettings
Requires-Dist: collective.volto.secondarymenu
Requires-Dist: redturtle.faq
Requires-Dist: redturtle.bandi
Requires-Dist: redturtle.rssservice
Requires-Dist: collective.volto.subsites
Requires-Dist: redturtle.voltoplugin.editablefooter
Requires-Dist: collective.volto.subfooter
Requires-Dist: collective.volto.formsupport
Provides-Extra: test
Requires-Dist: plone.app.testing ; extra == 'test'
Requires-Dist: plone.testing >=5.0.0 ; extra == 'test'
Requires-Dist: plone.app.contenttypes ; extra == 'test'
Requires-Dist: plone.app.robotframework[debug] ; extra == 'test'
Requires-Dist: collective.MockMailHost ; extra == 'test'
